parse_pdf/__init__.py
parse_pdf-0.1.0.dist-info/LICENSE
parse_pdf-0.1.0.dist-info/METADATA
parse_pdf-0.1.0.dist-info/WHEEL
parse_pdf-0.1.0.dist-info/RECORD
