Metadata-Version: 2.1
Name: parse-pdf
Version: 0.1.0
Summary: A PDF parser optimized for generating structured data.
License: MIT
Author: Aivin V. Solatorio
Author-email: avsolatorio@gmail.com
Requires-Python: >=3.10,<4.0
Classifier: License :: OSI Approved :: MIT License
Classifier: Programming Language :: Python :: 3
Classifier: Programming Language :: Python :: 3.10
Classifier: Programming Language :: Python :: 3.11
Requires-Dist: PyMuPDF (>=1.24.10,<2.0.0)
Requires-Dist: Rtree (>=1.3.0,<2.0.0)
